oneai/__init__.py
oneai/classes.py
oneai/clustering.py
oneai/exceptions.py
oneai/logger.py
oneai/output.py
oneai/parsing.py
oneai/pipeline.py
oneai/process_scheduler.py
oneai/skills.py
oneai/util.py
oneai/api/__init__.py
oneai/api/clustering.py
oneai/api/output.py
oneai/api/pipeline.py
oneai-0.9.89.dist-info/LICENSE
oneai-0.9.89.dist-info/METADATA
oneai-0.9.89.dist-info/WHEEL
oneai-0.9.89.dist-info/top_level.txt
oneai-0.9.89.dist-info/RECORD
