Metadata-Version: 2.1
Name: oneai
Version: 0.9.89
Summary: NLP as a Service
Home-page: https://github.com/power-of-language/oneai-sdk-python
Author: Michael Gur
Author-email: devrel@oneai.com
Project-URL: Bug Tracker, https://github.com/power-of-language/oneai-sdk-python/issues
Classifier: Programming Language :: Python :: 3
Requires-Python: >=3.7
License-File: LICENSE
Requires-Dist: aiohttp
Requires-Dist: validators
Requires-Dist: typing-extensions
Requires-Dist: requests
Requires-Dist: python-dateutil
Requires-Dist: dataclasses ; python_version < "3.7"
Provides-Extra: testing
Requires-Dist: pytest ; extra == 'testing'
Requires-Dist: pytest-cov ; extra == 'testing'
Requires-Dist: pytest-asyncio ; extra == 'testing'
Requires-Dist: pytest-dependency ; extra == 'testing'
Requires-Dist: mypy ; extra == 'testing'
Requires-Dist: python-dotenv ; extra == 'testing'
Requires-Dist: coveralls ; extra == 'testing'
